pyqqmusicapi/__init__.py
pyqqmusicapi/api/__init__.py
pyqqmusicapi/api/album.py
pyqqmusicapi/api/login.py
pyqqmusicapi/api/lyric.py
pyqqmusicapi/api/mv.py
pyqqmusicapi/api/playlist.py
pyqqmusicapi/api/search.py
pyqqmusicapi/api/singer.py
pyqqmusicapi/api/song.py
pyqqmusicapi/api/top.py
pyqqmusicapi/api/user.py
pyqqmusicapi/exceptions.py
pyqqmusicapi/helpers.py
pyqqmusicapi/qimei.py
pyqqmusicapi/qqmusic.py
pyqqmusicapi/utils.py
pyqqmusicapi-0.1.0.dist-info/LICENSE
pyqqmusicapi-0.1.0.dist-info/METADATA
pyqqmusicapi-0.1.0.dist-info/WHEEL
pyqqmusicapi-0.1.0.dist-info/RECORD
