Metadata-Version: 2.1
Name: pyqqmusicapi
Version: 0.1.0
Summary: QQ音乐API封装库
Home-page: https://github.com/luren-dc/QQMusicApi
License: MIT
Keywords: music,api,qqmusic
Author: Luren
Author-email: dluren.c@gmail.com
Maintainer: Luren
Maintainer-email: dluren.c@gmail.com
Requires-Python: >=3.8,<4.0
Classifier: Development Status :: 4 - Beta
Classifier: Framework :: Pytest
Classifier: Framework :: aiohttp
Classifier: License :: OSI Approved :: MIT License
Classifier: Natural Language :: Chinese (Simplified)
Classifier: Programming Language :: Python
Classifier: Programming Language :: Python :: 3
Classifier: Programming Language :: Python :: 3.8
Classifier: Programming Language :: Python :: 3.9
Classifier: Programming Language :: Python :: 3.10
Classifier: Programming Language :: Python :: 3.11
Classifier: Programming Language :: Python :: 3 :: Only
Classifier: Programming Language :: Python :: Implementation :: CPython
Classifier: Topic :: Software Development :: Libraries :: Python Modules
Requires-Dist: aiohttp (>=3.8.5,<4.0.0)
Requires-Dist: cryptography (>=41.0.2,<42.0.0)
Requires-Dist: requests (>=2.31.0,<3.0.0)
Project-URL: Documentation, https://luren-dc.github.io/QQMusicApi/
Project-URL: Repository, https://github.com/luren-dc/QQMusicApi
